thunderbolt/__init__.py
thunderbolt/client/__init__.py
thunderbolt/client/gcs_client.py
thunderbolt/client/local_cache.py
thunderbolt/client/local_directory_client.py
thunderbolt/client/s3_client.py
thunderbolt/thunderbolt.py
thunderbolt-0.1.2.dist-info/LICENSE
thunderbolt-0.1.2.dist-info/WHEEL
thunderbolt-0.1.2.dist-info/METADATA
thunderbolt-0.1.2.dist-info/RECORD
