Metadata-Version: 2.1
Name: thunderbolt
Version: 0.1.2
Summary: gokart file downloader
Home-page: https://github.com/m3dev/thunderbolt
License: MIT
Author: vaaaaanquish
Author-email: 6syun9@gmail.com
Requires-Python: >=3.7.1,<3.11
Classifier: License :: OSI Approved :: MIT License
Classifier: Programming Language :: Python :: 3
Classifier: Programming Language :: Python :: 3.10
Classifier: Programming Language :: Python :: 3.8
Classifier: Programming Language :: Python :: 3.9
Requires-Dist: boto3
Requires-Dist: gokart
Requires-Dist: tqdm
Project-URL: Repository, https://github.com/m3dev/thunderbolt
